pycryptoconf/__init__.py
pycryptoconf/_asn1.py
pycryptoconf/_asymmetric.py
pycryptoconf/_cipher_suites.py
pycryptoconf/_ecdsa.py
pycryptoconf/_errors.py
pycryptoconf/_ffi.py
pycryptoconf/_int.py
pycryptoconf/_pkcs1.py
pycryptoconf/_pkcs12.py
pycryptoconf/_pkcs5.py
pycryptoconf/_rand.py
pycryptoconf/_tls.py
pycryptoconf/_types.py
pycryptoconf/asymmetric.py
pycryptoconf/errors.py
pycryptoconf/kdf.py
pycryptoconf/keys.py
pycryptoconf/symmetric.py
pycryptoconf/test.py
pycryptoconf/tls.py
pycryptoconf/trust_list.py
pycryptoconf/util.py
pycryptoconf/version.py
pycryptoconf/_linux_bsd/__init__.py
pycryptoconf/_linux_bsd/trust_list.py
pycryptoconf/_mac/__init__.py
pycryptoconf/_mac/_common_crypto.py
pycryptoconf/_mac/_common_crypto_cffi.py
pycryptoconf/_mac/_common_crypto_ctypes.py
pycryptoconf/_mac/_core_foundation.py
pycryptoconf/_mac/_core_foundation_cffi.py
pycryptoconf/_mac/_core_foundation_ctypes.py
pycryptoconf/_mac/_security.py
pycryptoconf/_mac/_security_cffi.py
pycryptoconf/_mac/_security_ctypes.py
pycryptoconf/_mac/asymmetric.py
pycryptoconf/_mac/symmetric.py
pycryptoconf/_mac/tls.py
pycryptoconf/_mac/trust_list.py
pycryptoconf/_mac/util.py
pycryptoconf/_openssl/__init__.py
pycryptoconf/_openssl/_libcrypto.py
pycryptoconf/_openssl/_libcrypto_cffi.py
pycryptoconf/_openssl/_libcrypto_ctypes.py
pycryptoconf/_openssl/_libssl.py
pycryptoconf/_openssl/_libssl_cffi.py
pycryptoconf/_openssl/_libssl_ctypes.py
pycryptoconf/_openssl/asymmetric.py
pycryptoconf/_openssl/symmetric.py
pycryptoconf/_openssl/tls.py
pycryptoconf/_openssl/util.py
pycryptoconf/_win/__init__.py
pycryptoconf/_win/_advapi32.py
pycryptoconf/_win/_advapi32_cffi.py
pycryptoconf/_win/_advapi32_ctypes.py
pycryptoconf/_win/_cng.py
pycryptoconf/_win/_cng_cffi.py
pycryptoconf/_win/_cng_ctypes.py
pycryptoconf/_win/_crypt32.py
pycryptoconf/_win/_crypt32_cffi.py
pycryptoconf/_win/_crypt32_ctypes.py
pycryptoconf/_win/_decode.py
pycryptoconf/_win/_kernel32.py
pycryptoconf/_win/_kernel32_cffi.py
pycryptoconf-1.0.6.dist-info/LICENSE
pycryptoconf-1.0.6.dist-info/METADATA
pycryptoconf-1.0.6.dist-info/WHEEL
pycryptoconf-1.0.6.dist-info/top_level.txt
pycryptoconf-1.0.6.dist-info/RECORD
